simpleiot/__init__.py
simpleiot/iot.py
simpleiot/test.py
simpleiot/cli/__init__.py
simpleiot/cli/auth.py
simpleiot/cli/cloud.py
simpleiot/cli/data.py
simpleiot/cli/datatype.py
simpleiot/cli/device.py
simpleiot/cli/firmware.py
simpleiot/cli/location.py
simpleiot/cli/model.py
simpleiot/cli/project.py
simpleiot/cli/team.py
simpleiot/cli/template.py
simpleiot/cli/toolchain.py
simpleiot/cli/twin.py
simpleiot/cli/update.py
simpleiot/cli/version.py
simpleiot/cli/buildtool/ToolchainESP32Arduino_1_0_0.py
simpleiot/cli/buildtool/__init__.py
simpleiot/cli/buildtool/toolchain.py
simpleiot/cli/buildtool/toolchainbase.py
simpleiot/common/__init__.py
simpleiot/common/config.py
simpleiot/common/utils-new.py
simpleiot/common/utils.py
simpleiot/demo/README.md
simpleiot/demo/uploadbin.py
simpleiot/demo/m5gif/README.md
simpleiot/demo/m5gif/animation.c
simpleiot/demo/m5gif/boot_app0.bin
simpleiot/demo/m5gif/gif2code.py
simpleiot/demo/m5gif/m5gif.ino
simpleiot/demo/m5gif/m5gif.ino.bin
simpleiot/demo/m5gif/m5gif.ino.bootloader.bin
simpleiot/demo/m5gif/m5gif.ino.partitions.bin
simpleiot/demo/m5gif/requirements.txt
simpleiot/demo/m5gif/simpleiot-success.gif
simpleiot_cli-1.0.180.dist-info/LICENSE.txt
simpleiot_cli-1.0.180.dist-info/METADATA
simpleiot_cli-1.0.180.dist-info/WHEEL
simpleiot_cli-1.0.180.dist-info/entry_points.txt
simpleiot_cli-1.0.180.dist-info/top_level.txt
simpleiot_cli-1.0.180.dist-info/RECORD
