Metadata-Version: 2.1
Name: simpleiot-cli
Version: 1.0.180
Summary: SimpleIOT command line interface
Home-page: http://github.com/awslabs/simpleiot-cli
Author: Ramin Firoozye
Author-email: framin@amazon.com
License: Apache 2.0
Download-URL: https://github.com/awslabs/simpleiot-cli
Keywords: simpleiot,simpleiot-cli,iot,aws,awslabs,cli
Platform: UNKNOWN
Classifier: Environment :: Console
Classifier: Intended Audience :: Developers
Classifier: Intended Audience :: System Administrators
Classifier: Operating System :: Microsoft :: Windows
Classifier: Operating System :: MacOS :: MacOS X
Classifier: License :: OSI Approved :: Apache Software License
Classifier: Topic :: Software Development
Classifier: Topic :: Software Development :: Embedded Systems
Classifier: Topic :: System :: Hardware
Classifier: Topic :: System :: Installation/Setup
Classifier: Topic :: Utilities
Requires-Dist: arrow (==1.2.2)
Requires-Dist: asciimatics (==1.14.0)
Requires-Dist: attrs (==21.4.0)
Requires-Dist: aws-requests-auth (==0.4.3)
Requires-Dist: AWSIoTPythonSDK (==1.5.2)
Requires-Dist: backports.entry-points-selectable (==1.1.1)
Requires-Dist: bitstring (==3.1.9)
Requires-Dist: bleach (==5.0.0)
Requires-Dist: boto3 (==1.22.13)
Requires-Dist: botocore (==1.25.13)
Requires-Dist: certifi (==2022.12.7)
Requires-Dist: cffi (==1.15.0)
Requires-Dist: chardet (==4.0.0)
Requires-Dist: charset-normalizer (==2.0.12)
Requires-Dist: click (==8.1.3)
Requires-Dist: colorama (==0.4.4)
Requires-Dist: commonmark (==0.9.1)
Requires-Dist: coverage (==6.3.2)
Requires-Dist: cryptography (==38.0.3)
Requires-Dist: decorator (==5.1.1)
Requires-Dist: distlib (==0.3.4)
Requires-Dist: dnslib (==0.9.19)
Requires-Dist: dnspython (==2.2.1)
Requires-Dist: docker-py (==1.10.6)
Requires-Dist: docker-pycreds (==0.4.0)
Requires-Dist: docopt (==0.6.2)
Requires-Dist: docutils (==0.18.1)
Requires-Dist: ecdsa (==0.17.0)
Requires-Dist: esptool (==4.1)
Requires-Dist: filelock (==3.6.0)
Requires-Dist: future (==0.18.3)
Requires-Dist: idna (==3.3)
Requires-Dist: importlib-metadata (==4.11.3)
Requires-Dist: iniconfig (==1.1.1)
Requires-Dist: invoke (==1.7.1)
Requires-Dist: Jinja2 (==3.1.2)
Requires-Dist: jmespath (==1.0.0)
Requires-Dist: jsonschema (==4.5.1)
Requires-Dist: keyring (==23.5.0)
Requires-Dist: MarkupSafe (==2.1.1)
Requires-Dist: packaging (==21.3)
Requires-Dist: paho-mqtt (==1.6.1)
Requires-Dist: pbr (==5.9.0)
Requires-Dist: pexpect (==4.8.0)
Requires-Dist: Pillow (==9.3.0)
Requires-Dist: pkginfo (==1.8.2)
Requires-Dist: platformdirs (==2.5.2)
Requires-Dist: pluggy (==1.0.0)
Requires-Dist: prettytable (==3.3.0)
Requires-Dist: prompt-toolkit (==3.0.29)
Requires-Dist: ptyprocess (==0.7.0)
Requires-Dist: py (==1.11.0)
Requires-Dist: pyaes (==1.6.1)
Requires-Dist: pycparser (==2.21)
Requires-Dist: pyfiglet (==0.8.post1)
Requires-Dist: Pygments (==2.12.0)
Requires-Dist: PyJWT (==2.4.0)
Requires-Dist: pykwalify (==1.8.0)
Requires-Dist: pyparsing (==3.0.9)
Requires-Dist: pypng (==0.0.21)
Requires-Dist: pyrsistent (==0.18.1)
Requires-Dist: pyserial (==3.5)
Requires-Dist: pytest (==7.1.2)
Requires-Dist: pytest-html (==3.1.1)
Requires-Dist: pytest-metadata (==2.0.1)
Requires-Dist: python-box (==6.0.2)
Requires-Dist: python-dateutil (==2.8.2)
Requires-Dist: pyusb (==1.2.1)
Requires-Dist: PyYAML (==6.0)
Requires-Dist: questionary (==1.10.0)
Requires-Dist: readme-renderer (==35.0)
Requires-Dist: reedsolo (==1.5.4)
Requires-Dist: requests (==2.27.1)
Requires-Dist: requests-aws4auth (==1.1.2)
Requires-Dist: requests-toolbelt (==0.9.1)
Requires-Dist: rfc3986 (==2.0.0)
Requires-Dist: rich (==12.4.1)
Requires-Dist: ruamel.yaml (==0.17.21)
Requires-Dist: ruamel.yaml.clib (==0.2.6)
Requires-Dist: s3transfer (==0.5.2)
Requires-Dist: semver (==2.13.0)
Requires-Dist: six (==1.16.0)
Requires-Dist: sqlitedict (==2.0.0)
Requires-Dist: stevedore (==3.5.0)
Requires-Dist: termcolor (==1.1.0)
Requires-Dist: toml (==0.10.2)
Requires-Dist: tomli (==2.0.1)
Requires-Dist: tqdm (==4.64.0)
Requires-Dist: twine (==4.0.0)
Requires-Dist: typing-extensions (==4.2.0)
Requires-Dist: urllib3 (==1.26.9)
Requires-Dist: validators (==0.19.0)
Requires-Dist: virtualenv (==20.14.1)
Requires-Dist: wcwidth (==0.2.5)
Requires-Dist: webencodings (==0.5.1)
Requires-Dist: websocket-client (==1.3.2)
Requires-Dist: yaspin (==2.1.0)
Requires-Dist: zipp (==3.8.0)
